eval_ab_3d_mot/__init__.py
eval_ab_3d_mot/box_overlap.py
eval_ab_3d_mot/evaluate.py
eval_ab_3d_mot/evaluate_and_report.py
eval_ab_3d_mot/kitti_category.py
eval_ab_3d_mot/raise_if_sick.py
eval_ab_3d_mot/stat.py
eval_ab_3d_mot/thresholds.py
eval_ab_3d_mot/track_data.py
eval_ab_3d_mot/cli/__init__.py
eval_ab_3d_mot/cli/ab_3d_mot/__init__.py
eval_ab_3d_mot/cli/ab_3d_mot/ab_3d_mot_main.py
eval_ab_3d_mot/cli/ab_3d_mot/cmd_line.py
eval_ab_3d_mot/cli/batch_ab_3d_mot/__init__.py
eval_ab_3d_mot/cli/batch_ab_3d_mot/batch_ab_3d_mot_main.py
eval_ab_3d_mot/cli/batch_ab_3d_mot/cmd_line_factory.py
eval_ab_3d_mot/cli/batch_ab_3d_mot/cmd_line_object.py
eval_ab_3d_mot/cli/batch_ab_3d_mot_annotations/__init__.py
eval_ab_3d_mot/cli/batch_ab_3d_mot_annotations/batch_ab_3d_mot_annotations_main.py
eval_ab_3d_mot/cli/batch_ab_3d_mot_annotations/cmd_line_factory.py
eval_ab_3d_mot/cli/batch_ab_3d_mot_annotations/cmd_line_object.py
eval_ab_3d_mot/cli/batch_eval_ab_3d_mot/__init__.py
eval_ab_3d_mot/cli/batch_eval_ab_3d_mot/batch_eval_ab_3d_mot_main.py
eval_ab_3d_mot/cli/batch_eval_ab_3d_mot/cmd_line.py
eval_ab_3d_mot/cli/clavia/__init__.py
eval_ab_3d_mot/cli/clavia/bin_class_ratios.py
eval_ab_3d_mot/cli/clavia/clavia_main.py
eval_ab_3d_mot/cli/clavia/cmd_line_factory.py
eval_ab_3d_mot/cli/clavia/cmd_line_object.py
eval_ab_3d_mot/cli/clavia/pry_ab_3d_mot_association.py
eval_ab_3d_mot/cli/common/__init__.py
eval_ab_3d_mot/cli/common/ab_3d_mot_parameters.py
eval_ab_3d_mot/cli/common/annotation_num_frames.py
eval_ab_3d_mot/cli/common/get_hlp.py
eval_ab_3d_mot/cli/common/init_coinciding_attrs.py
eval_ab_3d_mot/cli/common/kitti_adaptor.py
eval_ab_3d_mot/cli/common/kitti_category.py
eval_ab_3d_mot/cli/common/r_cnn_adaptor.py
eval_ab_3d_mot/cli/common/single_sequence.py
eval_ab_3d_mot/cli/common/tracker_factory.py
eval_ab_3d_mot/cli/common/tracker_meta.py
eval_ab_3d_mot/cli/common/tracking_io.py
eval_ab_3d_mot/cli/evaluate/__init__.py
eval_ab_3d_mot/cli/evaluate/cmd_line.py
eval_ab_3d_mot-2.2.1.dist-info/METADATA
eval_ab_3d_mot-2.2.1.dist-info/WHEEL
eval_ab_3d_mot-2.2.1.dist-info/entry_points.txt
eval_ab_3d_mot-2.2.1.dist-info/licenses/LICENSE
eval_ab_3d_mot-2.2.1.dist-info/RECORD
