Metadata-Version: 2.4
Name: eval-ab-3d-mot
Version: 2.2.1
Summary: Evaluation for the Pure AB-3D-MOT.
Project-URL: Repository, https://github.com/kovalp/eval-ab-3d-mot
Project-URL: ChangeLog, https://github.com/kovalp/eval-ab-3d-mot/blob/main/CHANGELOG.md
Author-email: Xinshuo Weng <xinshuo.weng@gmail.com>
Maintainer-email: Peter Koval <koval.peter@gmail.com>
License-File: LICENSE
Keywords: ClavIA,ClearMOT,Evaluation of multi-object tracking,MOTA,baseline for nuScenes
Requires-Python: >=3.8
Requires-Dist: binary-classification-ratios>=0.3.0
Requires-Dist: munkres>=1.1.4
Requires-Dist: pure-ab-3d-mot>=2.1.0
Requires-Dist: pydantic>=2.10.6
Requires-Dist: pytest-mock>=3.14.1
Requires-Dist: rich-argparse>=1.7.1
Requires-Dist: rich>=14.2.0
Requires-Dist: scipy-stubs>=1.14.1.3; python_version > '3.9'
Requires-Dist: scipy>=1.10.1
